[
  {
    "id": 1,
    "name": "Event 1",
    "description": "Test",
    "date": 148654864,
    "place": "Boloto",
    "backgroundUrl": "www.google.com",
    "joinedUsers": [
      {
        "nickname": "owner",
        "name": "John",
        "surname": "Doe",
        "avatarUrl": "www.google.com",
        "phone": "380964851861"
      }
    ]
  },
  {
    "id": 3,
    "name": "Event 3",
    "description": "Test",
    "date": 148654864,
    "place": "Boloto",
    "backgroundUrl": "www.google.com",
    "joinedUsers": [
      {
        "nickname": "player",
        "name": "John",
        "surname": "Doe",
        "avatarUrl": "www.google.com",
        "phone": "380964851861"
      },
      {
        "nickname": "player2",
        "name": "John",
        "surname": "Doe",
        "avatarUrl": "www.google.com",
        "phone": "380964851861"
      }
    ]
  },
  {
    "id": 2,
    "name": "Event 2",
    "description": "Test",
    "date": 1486548643,
    "place": "Boloto",
    "backgroundUrl": "www.google.com",
    "joinedUsers": [
      {
        "nickname": "fan",
        "name": "John",
        "surname": "Doe",
        "avatarUrl": "www.google.com",
        "phone": "380964851861"
      }
    ]
  }
]